README.md
setup.py
translate_test/__init__.py
translate_test/settings.py
translate_test.egg-info/PKG-INFO
translate_test.egg-info/SOURCES.txt
translate_test.egg-info/dependency_links.txt
translate_test.egg-info/top_level.txt
translate_test.egg-info/zip-safe
translate_test/api/__init__.py
translate_test/api/v1/__init__.py
translate_test/common/__init__.py
translate_test/model/__init__.py
translate_test/model/pages.py
translate_test/model/rank.py
translate_test/service/__init__.py
translate_test/service/translate.py