Metadata-Version: 1.1
Name: translate-test
Version: 0.1.0
Summary: sogou
Home-page: https://github.com/mydu27/deemo
Author: chen
Author-email: chenjiageng@geekpark.net
License: UNKNOWN
Platform: UNKNOWN
Classifier: Programming Language :: Python
Classifier: Intended Audience :: Developers
